bruneus/__init__.py
bruneus/bruneus.py
bruneus/create_table.py
bruneus/export_table.py
bruneus/naming.py
bruneus/select.py
bruneus-0.1.11.dist-info/LICENSE
bruneus-0.1.11.dist-info/METADATA
bruneus-0.1.11.dist-info/WHEEL
bruneus-0.1.11.dist-info/top_level.txt
bruneus-0.1.11.dist-info/RECORD
