Metadata-Version: 2.1
Name: bruneus
Version: 0.1.11
Summary: bruneus: BigQuery helper utils.
Home-page: https://github.com/yokoe/bruneus
Author: yokoe
Author-email: kreuz45@kreuz45.com
Maintainer: yokoe
Maintainer-email: kreuz45@kreuz45.com
License: MIT
Download-URL: https://github.com/yokoe/bruneus
Keywords: bigquery
Platform: UNKNOWN
Classifier: License :: OSI Approved :: MIT License
Classifier: Programming Language :: Python :: 3.6
License-File: LICENSE
Requires-Dist: google-cloud-bigquery (>=3.4.0)
Requires-Dist: Jinja2 (>=3.0.0)
Requires-Dist: pandas (>=1.4.0)
Requires-Dist: db-dtypes (>=1.0.5)
